{
  "format_version": "1.12",
  "minecraft:recipe_shaped": {
    "description": {
      "identifier": "recipes_507489ea"
    },
    "tags": [
      "crafting_table",
      "Block_tool improvement table_custom"
    ],
    "pattern": [
      "A",
      "B"
    ],
    "key": {
      "A": {
        "item": "rex:wickedcrystal",
        "data": 0
      },
      "B": {
        "item": "rex:cdiamondpgold",
        "data": 0
      }
    },
    "result": {
      "item": "rex:cdiamondpgoldmcrystal",
      "count": 1
    }
  }
}