{
  "format_version": "1.12",
  "minecraft:recipe_shaped": {
    "description": {
      "identifier": "recipes_666863e7"
    },
    "tags": [
      "crafting_table",
      "Block_tool improvement table_custom"
    ],
    "pattern": [
      " A ",
      "ABA",
      " A "
    ],
    "key": {
      "A": {
        "item": "minecraft:redstone_block",
        "data": 0
      },
      "B": {
        "item": "rex:castralpdiamondpicmobsidian",
        "data": 0
      }
    },
    "result": {
      "item": "rex:castralpdiamondpicmobsidianmredstone",
      "count": 1
    }
  }
}